fw_gear_form_importer/__init__.py
fw_gear_form_importer/main.py
fw_gear_form_importer/parser.py
fw_gear_form_importer/util.py
fw_gear_form_importer/files/__init__.py
fw_gear_form_importer/files/fw_file_json.py
fw_gear_form_importer/files/json_file.py
fw_gear_form_importer-0.3.2.dist-info/METADATA
fw_gear_form_importer-0.3.2.dist-info/WHEEL
fw_gear_form_importer-0.3.2.dist-info/licenses/LICENSE
fw_gear_form_importer-0.3.2.dist-info/RECORD
