Metadata-Version: 2.4
Name: fw-gear-form-importer
Version: 0.3.2
Summary: Extract data from input form to Flywheel.
Author-email: Flywheel <support@flywheel.io>
License-Expression: MIT
License-File: LICENSE
Requires-Python: <4,>=3.12
Requires-Dist: flywheel-gear-toolkit>=0.6.22
Requires-Dist: flywheel-sdk<21,>=20
Requires-Dist: fw-file>=4.2.1
